odoo10_addon_analytic_tag_dimension_purchase_warning-10.0.1.0.0-py2.7-nspkg.pth
odoo/addons/analytic_tag_dimension_purchase_warning/README.rst
odoo/addons/analytic_tag_dimension_purchase_warning/__init__.py
odoo/addons/analytic_tag_dimension_purchase_warning/__manifest__.py
odoo/addons/analytic_tag_dimension_purchase_warning/models/__init__.py
odoo/addons/analytic_tag_dimension_purchase_warning/models/purchase.py
odoo10_addon_analytic_tag_dimension_purchase_warning-10.0.1.0.0.dist-info/DESCRIPTION.rst
odoo10_addon_analytic_tag_dimension_purchase_warning-10.0.1.0.0.dist-info/METADATA
odoo10_addon_analytic_tag_dimension_purchase_warning-10.0.1.0.0.dist-info/RECORD
odoo10_addon_analytic_tag_dimension_purchase_warning-10.0.1.0.0.dist-info/WHEEL
odoo10_addon_analytic_tag_dimension_purchase_warning-10.0.1.0.0.dist-info/metadata.json
odoo10_addon_analytic_tag_dimension_purchase_warning-10.0.1.0.0.dist-info/namespace_packages.txt
odoo10_addon_analytic_tag_dimension_purchase_warning-10.0.1.0.0.dist-info/top_level.txt
